{"cameraMode":{"drawMode":0,"name":"Shaded","section":"Shading Mode"},"sceneLighting":true,"audioPlay":false,"sceneViewState":{"m_AlwaysRefresh":false,"showFog":true,"showSkybox":true,"showFlares":true,"showImageEffects":true,"showParticleSystems":true,"showVisualEffectGraphs":true,"m_FxEnabled":true},"in2DMode":false,"pivot":{"x":2.9879543781280519,"y":6.184130668640137,"z":8.252344131469727},"rotation":{"x":-0.008050795644521714,"y":-0.1122603639960289,"z":-0.0009097701986320317,"w":0.9936463236808777},"size":6.195090293884277,"orthographic":false}